secure_secrets_module/AES_GCM.py
secure_secrets_module/__init__.py
secure_secrets_module/files.py
secure_secrets_module/secure_secrets.py
hc671123_secure_secrets-2.2.0.dist-info/METADATA
hc671123_secure_secrets-2.2.0.dist-info/WHEEL
hc671123_secure_secrets-2.2.0.dist-info/top_level.txt
hc671123_secure_secrets-2.2.0.dist-info/RECORD
