Metadata-Version: 2.4
Name: hc671123_secure_secrets
Version: 2.2.0
Summary: Module which enables storing encrypted, password protected secrets in a single file. Also allows for easy encryption and decryption of data
Author-email: hc671123 <behoben_floral0p@icloud.com>
Maintainer-email: hc671123 <behoben_floral0p@icloud.com>
License-Expression: MIT
Project-URL: Homepage, https://github.com/hc671123/secure_secrets_module-py
Project-URL: Repository, https://github.com/hc671123/secure_secrets_module-py.git
Project-URL: Issues, https://github.com/hc671123/secure_secrets_module-py/issues
Keywords: secrets,secure,encryption
Classifier: Intended Audience :: Developers
Classifier: Development Status :: 5 - Production/Stable
Classifier: Programming Language :: Python
Classifier: Programming Language :: Python :: 3.13
Requires-Python: >=3.13
Requires-Dist: pycryptodomex>=3.23.0
